mcdeck/__init__.py
mcdeck/marvelcdb.py
mcdeck/octgn.py
mcdeck/script.py
mcdeck/settings.py
mcdeck/tts.py
mcdeck/util.py
MCdeck-0.6.6.dist-info/COPYING
MCdeck-0.6.6.dist-info/LICENSE
MCdeck-0.6.6.dist-info/METADATA
MCdeck-0.6.6.dist-info/WHEEL
MCdeck-0.6.6.dist-info/entry_points.txt
MCdeck-0.6.6.dist-info/top_level.txt
MCdeck-0.6.6.dist-info/RECORD
