Metadata-Version: 2.1
Name: MCdeck
Version: 0.6.6
Summary: Custom card deck builder for Marvel Champions: TCG
Home-page: https://github.com/lcgtools/MCdeck
Author: Cloudberries
Author-email: lcgtools@proton.me
License: GNU LGPL v3 or later
Project-URL: Bug Tracker, https://github.com/lcgtools/MCdeck/issues
Keywords: lcgtools,lcg
Classifier: Development Status :: 3 - Alpha
Classifier: Intended Audience :: End Users/Desktop
Classifier: License :: OSI Approved :: GNU General Public License v3 or later (GPLv3+)
Classifier: Natural Language :: English
Classifier: Operating System :: OS Independent
Classifier: Programming Language :: Python :: 3
Classifier: Topic :: Utilities
Requires-Python: <4,>=3.9
License-File: LICENSE
License-File: COPYING
Requires-Dist: lcgtools ==0.5.7
Requires-Dist: PySide6
